odoo/addons/mrp_workcenter_category/README.rst
odoo/addons/mrp_workcenter_category/__init__.py
odoo/addons/mrp_workcenter_category/__manifest__.py
odoo/addons/mrp_workcenter_category/demo/mrp_workcenter_category.xml
odoo/addons/mrp_workcenter_category/i18n/it.po
odoo/addons/mrp_workcenter_category/i18n/mrp_workcenter_category.pot
odoo/addons/mrp_workcenter_category/models/__init__.py
odoo/addons/mrp_workcenter_category/models/mrp_workcenter.py
odoo/addons/mrp_workcenter_category/models/mrp_workcenter_category.py
odoo/addons/mrp_workcenter_category/readme/CONTRIBUTORS.rst
odoo/addons/mrp_workcenter_category/readme/DESCRIPTION.rst
odoo/addons/mrp_workcenter_category/security/ir.model.access.csv
odoo/addons/mrp_workcenter_category/static/description/icon.png
odoo/addons/mrp_workcenter_category/static/description/index.html
odoo/addons/mrp_workcenter_category/tests/__init__.py
odoo/addons/mrp_workcenter_category/tests/test_mrp_workcenter_category.py
odoo/addons/mrp_workcenter_category/views/mrp_workcenter.xml
odoo/addons/mrp_workcenter_category/views/mrp_workcenter_category.xml
odoo_addon_mrp_workcenter_category-15.0.1.0.0.8.dist-info/METADATA
odoo_addon_mrp_workcenter_category-15.0.1.0.0.8.dist-info/WHEEL
odoo_addon_mrp_workcenter_category-15.0.1.0.0.8.dist-info/top_level.txt
odoo_addon_mrp_workcenter_category-15.0.1.0.0.8.dist-info/RECORD
